silverware/HtmlFile.py
silverware/Spoon.py
silverware/__init__.py
silverware/clean_html_text.py
silverware/clean_name.py
silverware/clone_beautiful_soup_tag.py
silverware/exceptions.py
silverware/find_all.py
silverware/find_between.py
silverware/find_links.py
silverware/flatten_dictionaries_and_lists.py
silverware/get_lists.py
silverware/get_same_type_siblings.py
silverware/get_table_shape.py
silverware/get_text.py
silverware/get_url_and_get_anchor.py
silverware/read_table.py
silverware/separate_row_header.py
silverware/htmltext/BaseHtmlText.py
silverware/htmltext/HtmlText.py
silverware/htmltext/Section.py
silverware/htmltext/StructuredText.py
silverware/htmltext/__init__.py
silverware/htmltext/get_children.py
silverware/htmltext/get_font_size.py
silverware/htmltext/get_raw_text.py
silverware/htmltext/get_text.py
silverware/htmltext/is_body_text.py
silverware/htmltext/is_break.py
silverware/htmltext/is_bullet_point.py
silverware/string/__init__.py
silverware/string/ends_with_punctuation.py
silverware/string/get_alphabetic.py
silverware/string/get_alphabetic_ratio.py
silverware/string/get_numeric_ratio.py
silverware/string/get_words.py
silverware/string/is_capitalized.py
silverware/string/is_short_text.py
silverware/string/strip_non_alphanumeric_from_beginning.py
silverware/text/__init__.py
silverware/text/get_html_text.py
silverware/text/get_style.py
silverware/text/get_text_and_depth.py
silverware/text/merge_texts.py
silverware-2020.11.12.dist-info/LICENSE
silverware-2020.11.12.dist-info/METADATA
silverware-2020.11.12.dist-info/WHEEL
silverware-2020.11.12.dist-info/top_level.txt
silverware-2020.11.12.dist-info/RECORD
